MANIFEST.in
README.md
setup.py
transvenous_pacing_gui/__init__.py
transvenous_pacing_gui/client.py
transvenous_pacing_gui/gui.py
transvenous_pacing_gui/guiclient.py
transvenous_pacing_gui/guiserver.py
transvenous_pacing_gui/server.py
transvenous_pacing_gui/signals.json
transvenous_pacing_gui/signals.py
transvenous_pacing_gui.egg-info/PKG-INFO
transvenous_pacing_gui.egg-info/SOURCES.txt
transvenous_pacing_gui.egg-info/dependency_links.txt
transvenous_pacing_gui.egg-info/entry_points.txt
transvenous_pacing_gui.egg-info/requires.txt
transvenous_pacing_gui.egg-info/top_level.txt