Metadata-Version: 2.1
Name: transvenous-pacing-gui
Version: 0.7.88
Summary: Transvenous pacing procedure simulation GUI written in Python 3
Home-page: https://github.com/omn0mn0m/transvenous_pacing_gui
Author: Nam Tran, Cooper Pearson, Richie Beck, Marcel Isper, Brianna Cathey
Author-email: tranngocnam97@gmail.com
License: MIT license
Platform: UNKNOWN
Provides-Extra: testing
